bunnyshell/__init__.py
bunnyshell/_agent_client.py
bunnyshell/_async_client.py
bunnyshell/_client.py
bunnyshell/_utils.py
bunnyshell/_ws_client.py
bunnyshell/async_sandbox.py
bunnyshell/cache.py
bunnyshell/commands.py
bunnyshell/desktop.py
bunnyshell/env_vars.py
bunnyshell/errors.py
bunnyshell/files.py
bunnyshell/models.py
bunnyshell/models_updated.py
bunnyshell/sandbox.py
bunnyshell/terminal.py
bunnyshell/_generated/__init__.py
bunnyshell/_generated/models.py
bunnyshell/template/__init__.py
bunnyshell/template/build_flow.py
bunnyshell/template/builder.py
bunnyshell/template/file_hasher.py
bunnyshell/template/ready_checks.py
bunnyshell/template/tar_creator.py
bunnyshell/template/types.py
bunnyshell-0.1.10.dist-info/METADATA
bunnyshell-0.1.10.dist-info/WHEEL
bunnyshell-0.1.10.dist-info/RECORD
