Metadata-Version: 2.4
Name: bunnyshell
Version: 0.1.10
Summary: Official Python SDK for Bunnyshell Sandboxes
Project-URL: Homepage, https://bunnyshell.com
Project-URL: Documentation, https://docs.bunnyshell.com
Project-URL: Repository, https://github.com/bunnyshell/bunnyshell-python
Project-URL: Issues, https://github.com/bunnyshell/bunnyshell-python/issues
Author-email: Bunnyshell <support@bunnyshell.com>
License: MIT
Keywords: bunnyshell,cloud,containers,microvm,sandbox,vm
Classifier: Development Status :: 4 - Beta
Classifier: Intended Audience :: Developers
Classifier: License :: OSI Approved :: MIT License
Classifier: Programming Language :: Python :: 3
Classifier: Programming Language :: Python :: 3.8
Classifier: Programming Language :: Python :: 3.9
Classifier: Programming Language :: Python :: 3.10
Classifier: Programming Language :: Python :: 3.11
Classifier: Programming Language :: Python :: 3.12
Requires-Python: >=3.8
Requires-Dist: httpx>=0.25.0
Requires-Dist: pydantic>=2.0.0
Requires-Dist: typing-extensions>=4.5.0
Requires-Dist: websockets>=12.0
Provides-Extra: dev
Requires-Dist: black>=23.0.0; extra == 'dev'
Requires-Dist: mypy>=1.0.0; extra == 'dev'
Requires-Dist: pytest-asyncio>=0.21.0; extra == 'dev'
Requires-Dist: pytest>=7.0.0; extra == 'dev'
Requires-Dist: ruff>=0.1.0; extra == 'dev'
